CHANGES.rst
CONTRIBUTORS.rst
LICENSE.rst
MANIFEST.in
README.rst
buildout.cfg
setup.py
travis.cfg
bobtemplates/__init__.py
bobtemplates/hooks.py
bobtemplates.kitconcept.egg-info/PKG-INFO
bobtemplates.kitconcept.egg-info/SOURCES.txt
bobtemplates.kitconcept.egg-info/dependency_links.txt
bobtemplates.kitconcept.egg-info/namespace_packages.txt
bobtemplates.kitconcept.egg-info/not-zip-safe
bobtemplates.kitconcept.egg-info/requires.txt
bobtemplates.kitconcept.egg-info/top_level.txt
bobtemplates/plone_addon/.coveragerc.bob
bobtemplates/plone_addon/.editorconfig
bobtemplates/plone_addon/.gitattributes
bobtemplates/plone_addon/.gitignore.bob
bobtemplates/plone_addon/.mrbob.ini
bobtemplates/plone_addon/.travis.yml.bob
bobtemplates/plone_addon/CHANGES.rst.bob
bobtemplates/plone_addon/CONTRIBUTORS.rst.bob
bobtemplates/plone_addon/MANIFEST.in.bob
bobtemplates/plone_addon/README.rst.bob
bobtemplates/plone_addon/bootstrap-buildout.py
bobtemplates/plone_addon/buildout.cfg.bob
bobtemplates/plone_addon/setup.cfg.bob
bobtemplates/plone_addon/setup.py.bob
bobtemplates/plone_addon/travis.cfg.bob
bobtemplates/plone_addon/docs/LICENSE.GPL.bob
bobtemplates/plone_addon/docs/LICENSE.rst.bob
bobtemplates/plone_addon/docs/index.rst.bob
bobtemplates/plone_addon/src/+package.namespace+/__init__.py
bobtemplates/plone_addon/src/+package.namespace+/+package.name+/__init__.py.bob
bobtemplates/plone_addon/src/+package.namespace+/+package.name+/configure.zcml.bob
bobtemplates/plone_addon/src/+package.namespace+/+package.name+/interfaces.py.bob
bobtemplates/plone_addon/src/+package.namespace+/+package.name+/setuphandlers.py.bob
bobtemplates/plone_addon/src/+package.namespace+/+package.name+/testing.py.bob
bobtemplates/plone_addon/src/+package.namespace+/+package.name+/browser/__init__.py
bobtemplates/plone_addon/src/+package.namespace+/+package.name+/browser/configure.zcml.bob
bobtemplates/plone_addon/src/+package.namespace+/+package.name+/browser/overrides/.gitkeep
bobtemplates/plone_addon/src/+package.namespace+/+package.name+/browser/static/.gitkeep
bobtemplates/plone_addon/src/+package.namespace+/+package.name+/locales/+package.dottedname+.pot
bobtemplates/plone_addon/src/+package.namespace+/+package.name+/locales/update.sh.bob
bobtemplates/plone_addon/src/+package.namespace+/+package.name+/profiles/default/browserlayer.xml.bob
