Metadata-Version: 1.1
Name: bobtemplates.kitconcept
Version: 2.0.1
Summary: Templates for Plone projects.
Home-page: https://github.com/kitconcept/bobtemplates.kitconcept
Author: kitconcept GmbH
Author-email: info@kitconcept.com
License: GPL version 2
Keywords: web plone zope skeleton project
Platform: UNKNOWN
Classifier: Environment :: Console
Classifier: Intended Audience :: Developers
Classifier: Natural Language :: English
Classifier: Operating System :: OS Independent
Classifier: Programming Language :: Python
Classifier: Development Status :: 5 - Production/Stable
Classifier: Topic :: Software Development :: Code Generators
Classifier: Topic :: Utilities
Classifier: License :: OSI Approved :: GNU General Public License v2 (GPLv2)
